delphin/highlight.py
delphin.highlight-1.0.0.dist-info/DESCRIPTION.rst
delphin.highlight-1.0.0.dist-info/METADATA
delphin.highlight-1.0.0.dist-info/RECORD
delphin.highlight-1.0.0.dist-info/WHEEL
delphin.highlight-1.0.0.dist-info/metadata.json
delphin.highlight-1.0.0.dist-info/top_level.txt
