Metadata-Version: 2.0
Name: delphin.highlight
Version: 1.0.0
Summary: Pygments-based syntax highlighting for DELPH-IN formats.
Home-page: https://github.com/delph-in/delphin.highlight
Author: Michael Wayne Goodman
Author-email: goodman.m.w@gmail.com
License: MIT
Keywords: pygments highlighting delph-in linguistics
Platform: UNKNOWN
Classifier: Development Status :: 5 - Production/Stable
Classifier: Intended Audience :: Developers
Classifier: Intended Audience :: Information Technology
Classifier: Intended Audience :: Science/Research
Classifier: License :: OSI Approved :: MIT License
Classifier: Programming Language :: Python :: 3
Classifier: Programming Language :: Python :: 3.5
Classifier: Programming Language :: Python :: 3.6
Classifier: Programming Language :: Python :: 3.7
Classifier: Topic :: Software Development :: Libraries :: Python Modules
Classifier: Topic :: Text Processing :: Linguistic
Classifier: Topic :: Utilities
Requires-Dist: Pygments (>=2.3.1)
